biapy/__init__.py
biapy/_biapy.py
biapy/config/__init__.py
biapy/config/config.py
biapy/data/__init__.py
biapy/data/data_2D_manipulation.py
biapy/data/data_3D_manipulation.py
biapy/data/data_manipulation.py
biapy/data/dataset.py
biapy/data/norm.py
biapy/data/pre_processing.py
biapy/data/generators/__init__.py
biapy/data/generators/augmentors.py
biapy/data/generators/chunked_test_pair_data_generator.py
biapy/data/generators/pair_base_data_generator.py
biapy/data/generators/pair_data_2D_generator.py
biapy/data/generators/pair_data_3D_generator.py
biapy/data/generators/single_base_data_generator.py
biapy/data/generators/single_data_2D_generator.py
biapy/data/generators/single_data_3D_generator.py
biapy/data/generators/test_pair_data_generators.py
biapy/data/generators/test_single_data_generator.py
biapy/data/post_processing/__init__.py
biapy/data/post_processing/polygon_nms_postprocessing.py
biapy/data/post_processing/post_processing.py
biapy/data/post_processing/smooth_tiled_predictions.py
biapy/engine/__init__.py
biapy/engine/base_workflow.py
biapy/engine/check_configuration.py
biapy/engine/classification.py
biapy/engine/denoising.py
biapy/engine/detection.py
biapy/engine/image_to_image.py
biapy/engine/instance_seg.py
biapy/engine/metrics.py
biapy/engine/self_supervised.py
biapy/engine/semantic_seg.py
biapy/engine/super_resolution.py
biapy/engine/train_engine.py
biapy/engine/schedulers/__init__.py
biapy/engine/schedulers/warmup_cosine_decay.py
biapy/models/__init__.py
biapy/models/attention_unet.py
biapy/models/blocks.py
biapy/models/bmz_utils.py
biapy/models/dfcan.py
biapy/models/edsr.py
biapy/models/efficientnet.py
biapy/models/heads.py
biapy/models/hrnet.py
biapy/models/mae.py
biapy/models/memory_bank.py
biapy/models/multiresunet.py
biapy/models/rcan.py
biapy/models/resunet++.py
biapy/models/resunet.py
biapy/models/resunet_plus_plus.py
biapy/models/resunet_se.py
biapy/models/seunet.py
biapy/models/simple_cnn.py
biapy/models/tr_layers.py
biapy/models/unet.py
biapy-3.6.8.dist-info/licenses/LICENSE.md
biapy-3.6.8.dist-info/METADATA
biapy-3.6.8.dist-info/WHEEL
biapy-3.6.8.dist-info/entry_points.txt
biapy-3.6.8.dist-info/top_level.txt
biapy-3.6.8.dist-info/RECORD
