Metadata-Version: 2.4
Name: biapy
Version: 3.6.8
Summary: BiaPy: Bioimage analysis pipelines in Python
Author-email: Daniel Franco-Barranco <daniel.franco@dipc.org>
Maintainer-email: Daniel Franco-Barranco <daniel.franco@dipc.org>
License: MIT License
Project-URL: Homepage, https://biapyx.github.io
Project-URL: Source, https://github.com/BiaPyX/BiaPy
Project-URL: Forum, https://forum.image.sc/tag/biapy
Keywords: feed,reader,tutorial
Classifier: License :: OSI Approved :: MIT License
Classifier: Environment :: GPU :: NVIDIA CUDA :: 11.8
Classifier: Programming Language :: Python :: 3.10
Requires-Python: >=3.10
License-File: LICENSE.md
Requires-Dist: matplotlib>=3.7.1
Requires-Dist: scikit-learn>=1.4.0
Requires-Dist: pydot>=1.4.2
Requires-Dist: yacs>=0.1.8
Requires-Dist: tqdm>=4.66.1
Requires-Dist: scikit-image>=0.21.0
Requires-Dist: edt>=2.3.2
Requires-Dist: numpy>1.26
Requires-Dist: fill-voids>=2.0.6
Requires-Dist: opencv-python>=4.8.0.76
Requires-Dist: pandas>=1.5.3
Requires-Dist: torchinfo>=1.8.0
Requires-Dist: tensorboardX>=2.6.2.2
Requires-Dist: h5py>=3.9.0
Requires-Dist: zarr<3.0,>=2.16.1
Requires-Dist: bioimageio.core==0.8.0
Requires-Dist: imagecodecs>=2024.1.1
Requires-Dist: pooch>=1.8.1
Requires-Dist: xarray==2025.1.*
Requires-Dist: timm==1.0.14
Requires-Dist: pytorch-msssim
Requires-Dist: torchmetrics[image]==1.4.*
Requires-Dist: safetensors
Dynamic: license-file
